twitch_chat_analyzer/__init__.py
twitch_chat_analyzer/analyzer.py
twitch_chat_analyzer/downloader.py
twitch_chat_analyzer/kraken.py
twitch_chat_analyzer/models.py
twitch_chat_analyzer-0.0.5.dist-info/LICENSE
twitch_chat_analyzer-0.0.5.dist-info/METADATA
twitch_chat_analyzer-0.0.5.dist-info/WHEEL
twitch_chat_analyzer-0.0.5.dist-info/top_level.txt
twitch_chat_analyzer-0.0.5.dist-info/RECORD
