Metadata-Version: 2.1
Name: twitch-chat-analyzer
Version: 0.0.5
Summary: Twitch chat analyzer from past broadcasts, designed for Jupyter notebook
Home-page: https://github.com/c-rainbow/twitch-chat-analyzer-py
Author: Rainbow
Author-email: c.rainbow.678@gmail.com
License: UNKNOWN
Platform: UNKNOWN
Classifier: Programming Language :: Python :: 3.5
Classifier: License :: OSI Approved :: MIT License
Classifier: Operating System :: OS Independent
Requires-Python: >=3.5
